{
  "project_info": {
    "project_number": "870113131375",
    "firebase_url": "https://weather-project-4a5b2.firebaseio.com",
    "project_id": "weather-project-4a5b2",
    "storage_bucket": "weather-project-4a5b2.appspot.com"
  },
  "client": [
    {
      "client_info": {
        "mobilesdk_app_id": "1:870113131375:android:83b792e26f07bf18",
        "android_client_info": {
          "package_name": "com.example.android.sunshine.app"
        }
      },
      "oauth_client": [
        {
          "client_id": "870113131375-ij121vknndubu1ti5rtlrd13k0273ojk.apps.googleusercontent.com",
          "client_type": 3
        }
      ],
      "api_key": [
        {
          "current_key": "AIzaSyAgw3yDZ5xvlAjHi4ILx3c93b3stK6GWLw"
        }
      ],
      "services": {
        "analytics_service": {
          "status": 1
        },
        "appinvite_service": {
          "status": 1,
          "other_platform_oauth_client": []
        },
        "ads_service": {
          "status": 2
        }
      }
    }
  ],
  "configuration_version": "1"
}